dash_gantt/DashGantt.css
dash_gantt/DashGantt.py
dash_gantt/Grid.py
dash_gantt/HeaderRow.py
dash_gantt/TimelineBar.py
dash_gantt/TimelineLine.py
dash_gantt/TimelineRow.py
dash_gantt/__init__.py
dash_gantt/_imports_.py
dash_gantt/dash_gantt.min.js
dash_gantt/dash_gantt.min.js.map
dash_gantt/metadata.json
dash_gantt/package-info.json
dash_gantt-0.0.11.dist-info/LICENSE
dash_gantt-0.0.11.dist-info/METADATA
dash_gantt-0.0.11.dist-info/WHEEL
dash_gantt-0.0.11.dist-info/top_level.txt
dash_gantt-0.0.11.dist-info/RECORD
