Metadata-Version: 2.2
Name: dash_gantt
Version: 0.0.11
Summary: Create beautiful Gantt charts in Dash.
Author: Evan Rasmussen <evanras@umich.edu>
License: MIT
Classifier: Framework :: Dash
License-File: LICENSE
Dynamic: author
Dynamic: classifier
Dynamic: description
Dynamic: description-content-type
Dynamic: license
Dynamic: summary
